solar_client/__init__.py
solar_client/client.py
solar_client/connection.py
solar_client/exceptions.py
solar_client/resource.py
solar_client/api/__init__.py
solar_client/api/blocks.py
solar_client/api/delegates.py
solar_client/api/locks.py
solar_client/api/node.py
solar_client/api/peers.py
solar_client/api/rounds.py
solar_client/api/transactions.py
solar_client/api/votes.py
solar_client/api/wallets.py
solar_client-3.0.0.dist-info/LICENSE
solar_client-3.0.0.dist-info/METADATA
solar_client-3.0.0.dist-info/WHEEL
solar_client-3.0.0.dist-info/top_level.txt
solar_client-3.0.0.dist-info/RECORD
